cliclops/__init__.py
cliclops/parse.py
cliclops-0.0.1.dist-info/METADATA
cliclops-0.0.1.dist-info/WHEEL
cliclops-0.0.1.dist-info/RECORD
