Metadata-Version: 2.1
Name: cliclops
Version: 0.0.1
Summary: Small and simple command line arguments utilities
License: MIT
Author: Casey Walker
Requires-Python: >=3.11,<4.0
Classifier: License :: OSI Approved :: MIT License
Classifier: Programming Language :: Python :: 3
Classifier: Programming Language :: Python :: 3.11
Classifier: Programming Language :: Python :: 3.12
